ton/__init__.py
ton/errors.py
ton/sync.py
ton/tonlibjson.py
ton/account/__init__.py
ton/account/ft_methods.py
ton/account/nft_methods.py
ton/account/smc_methods.py
ton/account/state_methods.py
ton/account/wallet_methods.py
ton/client/__init__.py
ton/client/converter_methods.py
ton/client/function_methods.py
ton/client/tonlib_methods.py
ton/client/wallet_methods.py
ton/distlib/darwin/libtonlibjson.arm64.dylib
ton/distlib/darwin/libtonlibjson.x86_64.dylib
ton/distlib/freebsd/libtonlibjson.amd64.so
ton/distlib/linux/libtonlibjson.aarch64.so
ton/distlib/linux/libtonlibjson.x86_64.so
ton/distlib/windows/tonlibjson.amd64.dll
ton/tl/__init__.py
ton/tl/base.py
ton/tl/functions/__init__.py
ton/tl/functions/accounts.py
ton/tl/functions/keys.py
ton/tl/functions/queries.py
ton/tl/functions/settings.py
ton/tl/functions/smc.py
ton/tl/types/__init__.py
ton/tl/types/accounts.py
ton/tl/types/actions.py
ton/tl/types/keys.py
ton/tl/types/messages.py
ton/tl/types/smc.py
ton/tl/types/tvm.py
ton/tl/types/wallets.py
ton/utils/__init__.py
ton/utils/cell.py
ton/utils/common.py
ton/utils/wallet.py
ton-0.26.dist-info/LICENSE
ton-0.26.dist-info/METADATA
ton-0.26.dist-info/WHEEL
ton-0.26.dist-info/top_level.txt
ton-0.26.dist-info/zip-safe
ton-0.26.dist-info/RECORD
