Metadata-Version: 2.1
Name: ton
Version: 0.26
Summary: Python client for The Open Network
Home-page: https://github.com/psylopunk/pytonlib
Author: psylopunk
Author-email: psylopunk@protonmail.com
License: UNKNOWN
Platform: UNKNOWN
Classifier: Programming Language :: Python :: 3
Classifier: License :: OSI Approved :: MIT License
Classifier: Operating System :: OS Independent
Requires-Python: >=3.7
